CONTRIBUTING.md
LICENSE
MANIFEST.in
README.md
pyproject.toml
setup.cfg
setup.py
chemicalx/.DS_Store
chemicalx/__init__.py
chemicalx/constants.py
chemicalx/loss.py
chemicalx/pipeline.py
chemicalx/utils.py
chemicalx/version.py
chemicalx.egg-info/PKG-INFO
chemicalx.egg-info/SOURCES.txt
chemicalx.egg-info/dependency_links.txt
chemicalx.egg-info/requires.txt
chemicalx.egg-info/top_level.txt
chemicalx/__pycache__/__init__.cpython-38.pyc
chemicalx/__pycache__/constants.cpython-38.pyc
chemicalx/__pycache__/loss.cpython-38.pyc
chemicalx/__pycache__/pipeline.cpython-38.pyc
chemicalx/__pycache__/utils.cpython-38.pyc
chemicalx/__pycache__/version.cpython-38.pyc
chemicalx/data/__init__.py
chemicalx/data/batchgenerator.py
chemicalx/data/contextfeatureset.py
chemicalx/data/datasetloader.py
chemicalx/data/drugfeatureset.py
chemicalx/data/drugpairbatch.py
chemicalx/data/labeledtriples.py
chemicalx/data/utils.py
chemicalx/data/__pycache__/__init__.cpython-38.pyc
chemicalx/data/__pycache__/batchgenerator.cpython-38.pyc
chemicalx/data/__pycache__/contextfeatureset.cpython-38.pyc
chemicalx/data/__pycache__/datasetloader.cpython-38.pyc
chemicalx/data/__pycache__/drugfeatureset.cpython-38.pyc
chemicalx/data/__pycache__/drugpairbatch.cpython-38.pyc
chemicalx/data/__pycache__/labeledtriples.cpython-38.pyc
chemicalx/data/__pycache__/utils.cpython-38.pyc
chemicalx/models/__init__.py
chemicalx/models/base.py
chemicalx/models/caster.py
chemicalx/models/deepddi.py
chemicalx/models/deepdds.py
chemicalx/models/deepdrug.py
chemicalx/models/deepsynergy.py
chemicalx/models/epgcnds.py
chemicalx/models/gcnbmp.py
chemicalx/models/matchmaker.py
chemicalx/models/mhcaddi.py
chemicalx/models/mrgnn.py
chemicalx/models/ssiddi.py
chemicalx/models/__pycache__/__init__.cpython-38.pyc
chemicalx/models/__pycache__/base.cpython-38.pyc
chemicalx/models/__pycache__/caster.cpython-38.pyc
chemicalx/models/__pycache__/deepddi.cpython-38.pyc
chemicalx/models/__pycache__/deepdds.cpython-38.pyc
chemicalx/models/__pycache__/deepdrug.cpython-38.pyc
chemicalx/models/__pycache__/deepsynergy.cpython-38.pyc
chemicalx/models/__pycache__/epgcnds.cpython-38.pyc
