Metadata-Version: 2.1
Name: chemicalx
Version: 0.1.0
Summary: A Deep Learning Library for Drug Pair Scoring.
Home-page: https://github.com/AstraZeneca/chemicalx
Author: Benedek Rozemberczki and Charles Hoyt
Author-email: benedek.rozemberczki@gmail.com
License: Apache License, Version 2.0
Download-URL: https://github.com/AstraZeneca/chemicalx/archive/v0.1.0.tar.gz
Keywords: drug,deep-learning,deep-chemistry,deep-ai,torch-drug,synergy-prediction,synergy,drug-combination,deep-synergy,drug-interaction,chemistry,pharma
Platform: UNKNOWN
Classifier: Development Status :: 3 - Alpha
Classifier: Intended Audience :: Developers
Classifier: Topic :: Software Development :: Build Tools
Classifier: License :: OSI Approved :: Apache Software License
Classifier: Programming Language :: Python :: 3.7
Classifier: Programming Language :: Python :: 3.8
Classifier: Programming Language :: Python :: 3.9
Provides-Extra: tests
Provides-Extra: docs
